CHANGELOG.rst
LICENSE
MANIFEST.in
README.rst
requirements-3.txt
requirements.txt
setup.py
adium_sh.egg-info/PKG-INFO
adium_sh.egg-info/SOURCES.txt
adium_sh.egg-info/dependency_links.txt
adium_sh.egg-info/entry_points.txt
adium_sh.egg-info/not-zip-safe
adium_sh.egg-info/requires.txt
adium_sh.egg-info/top_level.txt
adiumsh/__init__.py
adiumsh/adiumsh.py
adiumsh/chat.py
adiumsh/command.py
adiumsh/settings.py
adiumsh/utils.py