Metadata-Version: 1.0
Name: adium-sh
Version: 0.2.0
Summary: Command-line wrapper of Adium
Home-page: https://github.com/shichao-an/adium-sh
Author: Shichao An
Author-email: shichao.an@nyu.edu
License: BSD
Keywords: adium
Platform: UNKNOWN
Classifier: Environment :: Console
Classifier: License :: OSI Approved :: BSD License
Classifier: Programming Language :: Python
Classifier: Programming Language :: Python :: 2
Classifier: Programming Language :: Python :: 3
